{
    "keyboard": {
        "name": "Razer Ornata Chroma",
        "zone": "Keyboard"
    },
    "backlight": {
        "name": "ASUS TUF GAMING B550M-PLUS",
        "zone": "Aura Addressable 1"
    },
    "home_assistant": {
        "url": "http://hass.kloud.home",
        "token": "",
        "sensor_id": "sensor.xperia_sp_light_sensor",
        "lux_threshold": 70,
        "poll_interval_seconds": 30,
        "dim_brightness_mult": 0.5
    },
    "notification_map": {
        "Thunderbird": {
            "color": "#0000ff",
            "flash_on_auto_close": "#00ffff",
            "flash_on_notify": false,
            "important": true
        },
        "Telegram Desktop": {
            "color": "#ffffff",
            "flash_on_auto_close": "#0000ff",
            "flash_on_notify": false,
            "important": true
        },
        "vesktop": {
            "color": "#ff00ff",
            "flash_on_auto_close": "#ffaaff",
            "flash_on_notify": false,
            "important": true
        }
    },
    "progress_map": {
        "application://firefox": "#ff4503",
        "application://org.kde.dolphin": "#03c2fc",
        "application://org.strawberrymusicplayer.strawberry.desktop": "#562b22"
    },
    "language_color_map": {
        "Russian": "#f322bc"
    }
}
